odoo/addons/l10n_it_sdi_channel/README.rst
odoo/addons/l10n_it_sdi_channel/__init__.py
odoo/addons/l10n_it_sdi_channel/__manifest__.py
odoo/addons/l10n_it_sdi_channel/data/config_parameter.xml
odoo/addons/l10n_it_sdi_channel/demo/sdi_channel_demo.xml
odoo/addons/l10n_it_sdi_channel/i18n/it.po
odoo/addons/l10n_it_sdi_channel/i18n/l10n_it_sdi_channel.pot
odoo/addons/l10n_it_sdi_channel/models/__init__.py
odoo/addons/l10n_it_sdi_channel/models/company.py
odoo/addons/l10n_it_sdi_channel/models/fetchmail_server.py
odoo/addons/l10n_it_sdi_channel/models/ir_mail_server.py
odoo/addons/l10n_it_sdi_channel/models/sdi.py
odoo/addons/l10n_it_sdi_channel/readme/CONFIGURE.rst
odoo/addons/l10n_it_sdi_channel/readme/CONTRIBUTORS.rst
odoo/addons/l10n_it_sdi_channel/readme/DESCRIPTION.rst
odoo/addons/l10n_it_sdi_channel/security/ir.model.access.csv
odoo/addons/l10n_it_sdi_channel/security/security.xml
odoo/addons/l10n_it_sdi_channel/static/description/icon.png
odoo/addons/l10n_it_sdi_channel/static/description/index.html
odoo/addons/l10n_it_sdi_channel/views/company_view.xml
odoo/addons/l10n_it_sdi_channel/views/fetchmail_server.xml
odoo/addons/l10n_it_sdi_channel/views/ir_mail_server.xml
odoo/addons/l10n_it_sdi_channel/views/sdi_view.xml
odoo11_addon_l10n_it_sdi_channel-11.0.1.0.0.99.dev7.dist-info/METADATA
odoo11_addon_l10n_it_sdi_channel-11.0.1.0.0.99.dev7.dist-info/WHEEL
odoo11_addon_l10n_it_sdi_channel-11.0.1.0.0.99.dev7.dist-info/top_level.txt
odoo11_addon_l10n_it_sdi_channel-11.0.1.0.0.99.dev7.dist-info/RECORD
